abcdrivers/__init__.py
abcdrivers/drivers.py
abcdrivers/data_files/MERRA2_U_VAREA_NH+SH_19800101-20210430.nc
abcdrivers/data_files/MJO_index.dat
abcdrivers/data_files/README.md
abcdrivers/data_files/__init__.py
abcdrivers/data_files/de421.bsp
abcdrivers/data_files/dstae.dat
abcdrivers/data_files/lat60N90N_Means_2hPa-100hPa.h5
abcdrivers/data_files/lat60S90S_Means_2hPa-100hPa.h5
abcdrivers/data_files/meiv2.data
abcdrivers/data_files/tci_info.txt
abcgan_drivers-1.0.0.dist-info/LICENSE
abcgan_drivers-1.0.0.dist-info/METADATA
abcgan_drivers-1.0.0.dist-info/WHEEL
abcgan_drivers-1.0.0.dist-info/entry_points.txt
abcgan_drivers-1.0.0.dist-info/top_level.txt
abcgan_drivers-1.0.0.dist-info/RECORD
