Metadata-Version: 2.1
Name: abcgan-drivers
Version: 1.0.0
Summary: ABC driver calculation
Author-email: Pablo Reyes <pablo.reyes@sri.com>, Leslie Lamarche <leslie.lamarche@sri.com>
Classifier: Programming Language :: Python :: 3
Classifier: License :: OSI Approved :: MIT License
Classifier: Operating System :: OS Independent
Requires-Python: >=3.7
License-File: LICENSE
Requires-Dist: numpy
Requires-Dist: scipy
Requires-Dist: h5py
Requires-Dist: flipchem
Requires-Dist: apexpy
Requires-Dist: skyfield
Requires-Dist: spacepy
Requires-Dist: pytz
